{
"2gkddaavsqxnp5hli74dm5pw":["ankuepfer","Andreas Küpfer"],
"7ipm6dmwcqxarwkveh4cfo3p":["anjapfeifer","Anja Pfeifer"],
"g6saqpdutubzdxiyt54xx4zr":["apfeifthewife","Allyson Pfeifer"],
"3mkvegl6kptbikvuwfr6cr2x":["arnaudpfef","Arnaud Pfeffer"],
"fnfvgwhhvajsgwzcqt2tzhsk":["asknezka","Nezka Pfeifer"],
"wwa4dtts6mo6zbqkpk4sxzgf":["ausraus","Nationalismus raus aus den Köpfen"],
"khexv6iamaer3ussdr4dbze3":["beccapfeiffer","Becca Pfeiffer"],
"64deo5z7owa757ncbx2g3yfc":["benjaminpfeifer","Benjamin Pfeifer"],
"7l7tsws4426cc2xazpqusmzy":["boopfeiffer","Boo Pfeiffer"],
"a72oezmo5iwhyqb5fk5owsw6":["borut","Borut Pfeifer"],
"tjscqoknz3srpiqyt5jblm25":["bsch","Basil Schläpfer"],
"74heamjpdgdbkptw7pqnyh3o":["candyman106","Ryan Pfeiffer"],
"zf4f7yh52muvzxwwphfrcnds":["carstenpfeiffer","Carsten Pfeiffer"],
"3mpl2o76s4wqzsv4kgtwm772":["clarapfeffer","Clara Pfeffer"],
"7d5iaslgbu7b7o7eqodz5ajy":["clemenspfe","Clemens Pfefferle"],
"zdayrkzf77r7fnto32qtnax3":["conanedogawa14","Pfeffica@onICE "],
"wcpnkdw7yc6hvuyrteeay5pf":["createperhaps","Kyle Pfeffer"],
"hrxnog7gnnowioyuk5onuvtw":["danpfeiffer","Dan Pfeiffer"],
"tcpkn5fxjpugeuc7woizoprj":["davidpfeifer","David Pfeifer"],
"mnuiisvlzimjdukhbzxxeppk":["derfussballpodcast.de","Becker & Pfeiffer - Der Fußballpodcast"],
"dieddz5ju63nmfjh5ytiipma":["derpfeffer","Der Pfeffer"],
"b6gtk33p7cghnotv3cjek34b":["diana-pfe","Diana 🌻🎃🍄"],
"oi5isqw4otxiyat3ht7srxxv":["digitalnaiv","DigitalNaiv = Stefan Pfeiffer"],
"ozps4otp53hkxo42fbjiaf4d":["digitoph","christoph pfeiler"],
"2gv6z2dl2dldb25gbuv46dlp":["dragonlady","Kate Pfeilschiefter"],
"nmpcb3xooxx4eklum2rlgqvz":["eblurbs","Eric Töpfer"],
"3u65mjy3owbn5hmlbfffeers":["elczar","pfeizer shakes"],
"w7ra2sxo4rfqnxc5uxefhseq":["empyria","Fraeulein Pfeffi"],
"dex5zd4kr7r4icm5syzaifkh":["ernegl95","Harald Töpfer"],
"p4er7oduecgu6pvtinve7zmd":["espfeffert","Nicole M. Pfeffer"],
"zosnvny3larlmjuut5neckhu":["fabianpfeffer","Fabian Pfeffer"],
"eypwu6jlj32bidsvog2urfzt":["frankwunderli13","Frank Wunderlich-Pfeiffer"],
"l2vnyzquw5idvzesh4om5lto":["fraupfeffertopf","Frau Pfeffertopf"],
"tpp7sqt6qm2o3binfwhrjize":["fredpf","Frederik Pfeiffer"],
"rkjaraqogm6rehzi3uag5ton":["geordi2504","Pingu mit Pfeife"],
"pau5asfqj5mlkotmacm6vofw":["genesys-experten","GENESYS - die kreativen Köpfe "],
"enhajdv3mdg2kawx2yvs5vxa":["gilapfeffer","Gila Pfeffer (as in ‘Havanagila)"],
"uw63h2iaadfuuv7xcyzuhxe2":["goepfe","Mirco Göpfert"],
"5fekktjgoxyu6uexr4p65as2":["goldschonerin"," zwei-Pfeile-Goldschonerin"],
"pkaq3rqv7z7o2pkd43pkupxk":["gregor-pfeifer","Gregor Pfeifer"],
"tpeswojmh6xll3r3sj34lwa7":["groogo","Pfeffienator"],
"w6az7jfpehxzsxgjtqvj5s2o":["isapfeiffer","Isabela Pfeiffer"],
"h75mgf6fcqn26kqzxfhzd2bd":["jenndsn","Dr. Jennifer Pfeifer "],
"ufkoaeta7icwnq7dzab3peq5":["jenpfeife","Jenny, die Pfeife"],
"gtqhqwqdquxpqvcxtnp34hbb":["jenspfeiler","Jens Pfeiler"],
"hri2df4pvw7kvx5in5exvwnv":["jkpfeiff","Julie Pfeiffer"],
"7ofhcassmkxejirxhzhi2x3j":["jonaspfeiffer","Jonas Pfeiffer"],
"qwz2jvernq2j7aexboatmrnw":["jpfeif4life","Josh \"JPfeif4Life\" Pfeif(er)"],
"okjl2npf6hk734anohesj6yy":["jpfeil","Jan Pfeil "],
"3pt5dflw7v3zx7pev6ytj4pg":["jurgenpfeffer","Jürgen Pfeffer"],
"gp2f63ikyhpiec2ls7hvp5fd":["juergenp78","Jürgen Pfeiffer "],
"kqir6t6qqcl63expnz4s5tuk":["jwupf.net","Jörg Wunderlich-Pfeiffer"],
"genw7qnupesxrp2ephyg3g45":["karlpfeifer","Karl Pfeifer"],
"q4wbggurpe4gsu3tg3r7lkex":["kleinepfeife","KleinePfeife "],
"ehewyyvkexzcbhbhwnjanzgu":["kpfennigwerth","Kim Pfennigwerth "],
"gczvvswap2wsazo2hyksnde5":["lacheimregen","Pfefferminzia"],
"kiguo4c6xf2ahck2xtjbdblb":["laurenpfeil","Lauren Pfeil"],
"3xwxytqmi5n27xdlf5g5774t":["leepfenninger","Lee Pfenninger"],
"2wjb3xnwmwq4eemjzr5f7ayn":["leapfeffer","Lea Pfeffermann"],
"jb7qk6hu2vsgvlelm32w2iyd":["louispfeiffer","Louis Pfeiffer "],
"44hf2g4otqnki63y4cp2eupc":["markpfeiffer","Mark Pfeiffer"],
"4byaqs3gl2ldqj7rgby2wens":["mattpfeff","Matt Pfeffer"],
"weoi2tnzyhb7mfqtwpbzicyl":["mattpfeiffer","Matt Pfeiffer"],
"de7mt4gzxrk3snkz3dbkkxyb":["marcelgoepfert","Marcel Göpfert"],
"btf73hnir7f4hdqyq4kqbt6h":["markusspfeffer","Markus S. Pfeffer 🌻"],
"tdnnocp4xi35gp7wsohdnitc":["mandy21","Mandy Pfeifer"],
"qchqnjuxezaquk3tn7mdvcpe":["mikefail","Mike Pfeil"],
"utr26k464kyr7k33iogigxvr":["micahjay","Micah Jay Pfeiffer"],
"rvwopmjvimarj3utdnj55hnp":["monsteramaus","ronja rosine das beste pferd im stall(herbts 🍂)"],
"cq2v24ufqgtm2lcsvmzokotf":["mpfef","Matt Pfeffer"],
"hl6vlhlzsnfa464zhxjdv7di":["mpfeifer","Markus Pfeifer "],
"qhalhswfud7ekegcqgp5nnv2":["muekke","Mücke das Pferd"],
"dtsykjr77xxov3yuaqkdgnyg":["naturefirst","IszaGrashüpfer"],
"xdtf6wibmifkx63q3gticjj6":["nickpfeiffer","Nick Pfeiffer"],
"5c36x3ihzpsfbo7b6j7jozum":["nilsftoepfer","Nils F. Töpfer, PhD"],
"7bnxq3tcvf3f7qpdwn63hevz":["niklaspfeiffer","Niklas Pfeiffer"],
"3nbbotog6cufvq5vga3n2e5c":["ninapfeil","Nina Pfeil"],
"ug27jry5yq3ljscgvodxnic5":["notiz.blog","Matthias Pfefferle"],
"5at5gikrfzvktcpmzmvzil2q":["nuclearanthro","Martin “Doomsday” Pfeiffer🏳️‍🌈"],
"amq3nwvi2a53fxofsrg7exlx":["pfessenbecker","Patrick Fessenbecker"],
"bymmdfkcgmqkmktntpk2yazr":["pfe3","Patricio Esparza III"],
"sux3vah2y5hyjbst6taiq4sp":["pferders","Dark Horse "],
"qqao6mc5g5dqsvstaf2r5vhk":"pfeffer",
"ynbwdpopruwpiumurlhumhzs":"pfeilbr",
"c2skjbfvflevgheqr77udu5m":"pfed",
"fkhrdvzu3ua4bk4syrvztlqb":"pfeff",
"rcy6nnzu6pzsnb47zqqt7i7v":["pfeiffer","James Pfeiffer"],
"5uwnzqbltom4oanqnczktmbr":["pfederman","Peter"],
"dqaoaxf3sfqaammjsby5w7uz":["pferguson","Patrick Ferguson"],
"3n4k27nlm3zb4rijy6vxpb6z":["pfefferbao","Pbao"],
"qe7p4fom3dkgpfaac3fkfuhr":["pfeilgradaus","SaBiNa"],
"ccm5oyjdu24tmahzcj4zb5zq":["pfefferminz","minz"],
"vws2qfcxxu2r77am4amzsglf":"pfenomenologist",
"kdk37hjiaqjlab5w5tyqgzt2":["pfeifedeggel","Pfeifedeggel"],
"dhmv4mio3i5wiy5dzatzhnot":"pferdeblut",
"724snjnytaze2lsz2rykpzcd":["pfez82","Pete Fez"],
"kgfqoklp3kmcu3xumsqmqypu":"pfess",
"gvfb4xkzc35dyc6byqya3inn":["pfeickert","Peter "],
"tqymm44lpucouhzy7eprsbdg":["pfeffaroo","pfeffaroo"],
"gvm6i3lskok5kybj3zbgi577":["pfellah","Jason McDonald"],
"spii3jh4pysngpn3k5rkrhyl":["pfeffifee","PrinzessinPfeffifee"],
"pryr3dnkldwtpakgqqgnwe5q":["pfeffi","🍵pfeffidenis🤗🐇"],
"sids7nmtghdtock5qz3elfyn":"pfeliks",
"tu3vettvivwxsmxkxxr6m26k":["pfeifferpack","Pfeifferpack aka Kathleen Pfeiffer"],
"6xlq6zci2w4443fj2dy45rt3":"pferdelasagne",
"37sjff5vy2dc7e3wiweebu4y":["pferdefreundin","Pferdefreundin "],
"qpqndv7eygmebyqbguc345nk":["pfeifer","Jacob Pfeifer"],
"d7ocwq5nd6ifobliug4q55dh":["pfeifferuk","clown"],
"ktya6endlzqkjfrzv76kwava":["pfeiffer42","Bernd Nossem"],
"3mkpcw4alg4sbzan3r4fphtq":["pferdigkuchenhon","wassër"],
"yc2zaplqkqxlheju72set37v":["pfeifhaas","Pfeifers"],
"qcj7xknf2drqsbbwfs3erpda":"pfeilstorch",
"xzsnreobtfbsjjapmunghvii":["pfersdorf","Treework #Fella #NAFO 💚🇺🇦🔱 "],
"xefbvur7qujmssjyxu3xgp7o":"pfennigfux",
"axi2dx4wtjldgej2yltpdpru":["pferdi","Master of #Pferdiverse 🤓"],
"3x3n2wm7tbauj5xxyatbmttp":"pferge",
"i6bl7w4t4lvmhsahgdhhph5m":["pfeifer-bley","Oskar Pfeifer-Bley"],
"hwk532rfyct7zddy2n5yekle":"pferdehexe",
"rgfrzufizmxuxce33sjndmvj":["pfefferminzboi","Nothing/To/You"],
"3eqqfxizjismq4kwnyyrb77z":"pfeffermin",
"3fvng226vtjyasfdu2j7rape":["pfontio","Pfenja"],
"cp5iuxklu5yi2uyenf5so5cr":"pfeldman",
"day5gwp6whjozoytkhhacsrm":["pfernando","Patrick Fernando Schneider"],
"cy4urknijr35oilbl3mz3u5y":["pfefferhasi","ulla scharfenberg "],
"4umomelgxksnyrxm2e4m3fdm":"pfeiseb",
"epynff2kccvgjffyra3fz4cq":["pfefferhaubitze","Pfefferhaubitze"],
"imxtf6hflngonvpulcrf4456":["pfefferminz11","Pfefferminz"],
"rnzt2mudxyo6sf6wdpkifwog":["pferdeantifa","Antifaschistische Pferdestaffel"],
"kdoc2ke2vf3z7kfl3r4mtccb":["pfennigfuchser","Pfennigfuchser"],
"jonhrkjqptwxckgznt2rbof7":["pfeffermuhle","mixed by paola"],
"hqmskd4mwoafd56rwvr2srj6":"pfeifferjake",
"jznnkge235x3tnflykrknpoy":["pfefferstroem","amalie_pfefferstroem"],
"nn3ccpmymuvpz2r5qgj7x5wf":["pfefferwiesalz","PfefferWieSalz"],
"uoalrki55furungtl3k3eerz":"pfefferminzia.de",
"pghqdleka6jjn6wrecdlilze":"pfeifenitler",
"zymmvdjdz7ik3b777uieyx5m":["pfeld","Paige Feldman"],
"2hgenmapjgri52odyg7fyy3d":["pfenning","pfenning"],
"zynci7eymbopmuxtl2s5n3mb":["pfeilo","Pfeilo161 🌱 "],
"j62vesh3tffrk6dfnllrug43":["pfeffermuenz","Pfeffermünz "],
"5wrxgokikl4dxovk4upnvvj2":["pfeiferocks","pfeiferocks"],
"7zeernevw6p5kl6xyf5jxqeo":["pferrandfresnel","Patrick Ferrand"],
"ces3ossqrqhry4y5nevacoyn":"pfefferwitch",
"ivewfe3hum5fybzpoaglqcmx":"pfenix",
"v6xtws4ymcdnbd7i7lk5457b":["pfeffermouse","Pfeffermouse"],
"yqbxjnvzvq3t2gylemeteteo":["polypepper","Anja Pfeffermann"],
"k5dpjvq6s5xdrwprgh57ypbq":["polygonas","Jonas Pfeiffer"],
"lvetja7ntlaodeofnhex2ozq":["qrdknpfr","Curd Knüpfer"],
"5gxcyzpcvynxoku5meznrnfn":["rafapfeifer","Rafa_Pfeifer"],
"dpx5y4b3gie35cjqo7ldnmyg":["reffeff","Ulrich Pfefferle"],
"2qxlbosxsyjjqxq2lih72wsf":["rynsays","Ryn Pfeuffer"],
"rinxoiadsrsg5zrir2aj26dq":["schluepferlady","Schlüpferlady"],
"mehbht6x5y3uwx45uik2mxih":["sebpfeffer","Sébastien Pfeffer"],
"4ugif2ru53xkwsxeuye3irwd":["spfeiffer","Stefan Pfeiffer"],
"fdjhdcnyau3jjta2cdnqomk5":["stefaniepfeiffer","Stefanie Pfeiffer "],
"tpmkxglujjxcwmiflv2k3wof":["sugarcubist","Pfersiche"],
"zoeqcqwi6oaw74ktd7lnokzj":["sylvioprauss","Sylvio Pfeiffer-Prauß "],
"esh6k3pcd3dnzughh7llvxhy":["thmspfffr","Thomas Pfeffer"],
"pxhivzm34vpz7f3ydjc7fbp5":["twelvem0nkeys","Altes Pferd "],
"imabdwygidr7ojemi46nilpm":["valentinpfeil","Valentin Pfeil"],
"7i7uop3s3ijaajvcddjs6men":["val-pfeifer","Valeria Pfeifer"],
"dqpckhhzyl5vgjliaukbfoty":["volkerpanzer","Volkmar Pfanner, geb. Töpfer"],
"jlssjlrvtyjxmrbjukuxvni4":["w9mhz","Mike Pfeifer"],
"u7afcf7zllyfsmfhrvzbcsq2":["werdaepfel","Werdäpfel"],
"w6mra25eau4ronj2mairmwcp":["willpfeifer","Will Pfeifer"],
"44dhdk7htquc6q7c3wupdhrh":["wortpiratin.de","Mara Pfeiffer"],
"xksugaa7nejzoyeyl4r7ze4w":["xlr","Armin Töpfer"]
}
