{
"a4bgxcwbg3575urrtamzflgx":"5peso",
"5b55naljcmqq6v4xsvdeyqrd":"50pesopaule",
"5vtjs6lft6fm5kpqn2htelqt":["abu-pessoptimist","Abu-pessoptimist"],
"nkgeaju4m6vncb4vjw56sfr4":["ahanenohi","Pesto "],
"wz5pvvgwydxq5rk2bdq33irm":["akipesa","AkiPesa"],
"bnylsrrn5kgcycps3b5ktoui":["alexrubner","Alex Rubner is a sex pest danger"],
"qchiwlx2jlzppcffsnxmqqeo":["alexmihawk","Alexandre Pessoa"],
"hijly4qxr7dndq2jommlifo3":["alexxstr1pes","Alexx"],
"x3pz2nwzditsipvrw5r4pwts":["amigapessoal","amiga pessoal"],
"hp5zv73vmc37wa3xdzvi4yow":["andreolle.pessoas.dev","Andreolle"],
"camxgru74n3zm2cdhrwankef":["anthonyjpesce","Anthony Pesce"],
"goxmm2x7bbdnjv2vzxvv6j3w":["anthonypesec","Anthony Pesec"],
"fdbveuaawacngsapfbbssy4t":["anticiv","anticop anarcho-pessimist hellfire preacher"],
"7cpaf6rktnyeabzzfp5a6rvb":["anoxysm","Pesto"],
"v43fchzsdjdwnbiwbd6dcmvl":["andreaspeschel","Andreas Peschel "],
"qqbhep7yldynzcfvvlef3odz":["annispessi","Anna-Mari Pessi "],
"3qfhltlqq7y2kre4egktwpwp":["apescador","Jéssica Pescador "],
"dbuprapw5dy4fptnjzaaqqby":["apeskypossum","Pesky Possum"],
"e5ev4wbftfzsgbnive2octg7":["arghno","Arnaud Pessey "],
"4pgppw7o5ong4npeciaozjoq":["aripeskoe","Ari Peskoe"],
"h3oi2aywyrfl6ecijm2eugvb":["barreto.pessoas.dev","barreto.vue"],
"qud75t73cswkea5s2onvjxko":["barranull.pessoas.dev","Lucas Freitas"],
"sp664tg3wkt5tjcrgu2mvgs6":["banzebanze","Bruno Pessanha"],
"v2ajwbb2ulw3olvkk7hrlhu7":["bdebeatriste","pessoa extremamente básica "],
"2zhydb5vzzbehwd4nw5qnmzh":["bellapessoa","Isabella Pessoa "],
"ucttfzopdpjouqk5aojrsiko":["benpester","Ben Pester"],
"vk7x3gn3jl3rdthmpiryggvl":["bekkafishy","Bekka Pesqueira"],
"odavztwd75gmx27eh3uccstv":["bpeso","Beñat Peso"],
"fw4bdzak26z2m6klzf3bzixa":["bunnyratto","Some Pest"],
"d2sgr32evapl27zi2c27kvju":["caterinafish","Caterina Pesce"],
"uogquyxrzmqcfcaeokrosbxw":["catchdacurve","Pesky Heaux "],
"j6hxpkpukkezmvgiem3qe3vw":["callithrix","PESTO FOREVER"],
"miojcojw5keg6voux747r65r":["cbutts72","Pessimistic Optimism "],
"6gu2yhi3neb47maakszohsdl":["chrissypeske","Chrissy Peske"],
"vz7bregy345ppgz3qx5lznmw":["classichoss","joe pesci from 2009"],
"3xijexj57xz4vxfwgnef6ug3":["cnerds","Ramon Pesante | Colorful Nerds "],
"gramym3q5pncs24ht6yylhzq":["coalhouse","Pessimist Prime"],
"dzsilcn2nzzgyvvqpibhoqeb":["colepessolano","Cole Pessolano"],
"prkinnkwhodd3e7kujd4nhqj":["cotti.moe","Cotti (a pessoa, não o sabor de sorvete)"],
"p74xe5lxacjphq7gwihog7po":["crestdraggy","Cresto Pesto"],
"3nrlptsnycc3qjuugfx5xd64":["cristiano27","Cristiano Pessoa "],
"jty2vyn33yweyag37pj3rvoi":["ctrlshiftt","Recuperar Pestaña "],
"xrxlrjywklqygnbl5k4hpkwn":["cueeyt","Rui Pestana "],
"s4vnsd63gefu6vltqa7ppqni":["danielpestner","Daniel Pestner"],
"jkhqljiujoo43gdmaajogz4c":["depesando","de Pesando"],
"vyobdhyb3bpy5vwfqc6q3mh5":["demoni","I demoni dalla cantina del Signore Pesci 📯"],
"i5v4cw6lrotyohf4l2nrjfb4":["debuggingwizard","digital pest control"],
"5hmvts2tzqm4edw4eqayhpca":["dereknshoes","Pesto"],
"l2n3e5xqm3bd54wy2gcjabtx":["dinutha","Dinutha Peshala"],
"4cirsnc6pnwggoaw52ghzr3x":["diegopessoa","Diego Pessoa"],
"lvfstg4bxoz2sj3zzqxrup2l":["djbluedapest","DJ BlueDaPest"],
"bnhwbyebwi5dsqisiu5xkmzw":["dpmpessoa","Daniel Pessoa"],
"gzv4epsf77swlcgikm3yf7lb":["dpesmen","dale pesmen"],
"ljlwpukhhc6d2vtp7a55lztb":["dumptruckderg","Dat Pesky Taki 🔞"],
"aogcfpbutoeqms2yof7y2ljg":["ellenvankeulen","NouraChodskyPes&Ellen "],
"hzi4hxbidpez54fzwh4j6vke":["elpescado","El Pescado"],
"lkuk4nfbyb6kk3sula2ls66r":["elainepessanha","Elaine Pessanha "],
"723cte3dehxfbcpn5xxocj4a":["emma-pesque","Emmanuelle Pesqué "],
"duevexmgsqxvk6xe4s6vji4i":["epesola","Eric Pesola"],
"nggymzk5ldrqwqohhorbalay":["esmilay","pesimist "],
"gpujrtbhaykjrydbggdk4kf3":["essapessoa","Essa Pessoa"],
"7gwul7xj7bfb2chuzayyemaf":["fallingupward","pessimistic person"],
"u4hmqqt6urredqwtvjnxbz7c":["fadiesismin","Peste Borbonica 👹🔞 HIATUS @ Zine&Commission 3/3"],
"2d5d57rtkupowvoh4yd6rf26":["fernandopessoa","Fernando Pessoa "],
"t6efi6go2s55ojoubgcyjxxh":["fededalpesco","Federica Dal Pesco"],
"z2gmqapmpiponhqexo2pyawn":["fleddiep","Ed Pesce"],
"bh4u5favysi2lj5kkvhbueuj":["forzapesh","Pesh"],
"ehfv6nlacrrrf524owmwi3cp":["frenchgouda","Pesto"],
"xmntkxzk27t6og76xdm6lnfu":["furypesto","Fury Pesto "],
"kom5nuxyzykjtaaeuxdz6rkg":["gameswithwine","Tom Peske"],
"trdjqzk7ahfwak47jim3aosk":["gabrielpessoa","Gabriel Pessoa"],
"jznwqgi56blkkeru36znldky":["gamespodcast","Andre Peschke"],
"cnnn6y4upfy3rzw3ztqoju27":["genealonet","Laëtitia Pessiot"],
"tjnp6pwlvtv33ys6x4qheovc":["ghostthekaos","Ghost is Working on 'PESADELO'"],
"rvarvu7l54lk3o4y6usanpul":["gnpestana","Gonçalo Pestana"],
"bebgyjenz4ewajkxtfunbfqz":["gremren","renata 🎷🐅 in my pest era ✨"],
"lta43kzugfxqwd23om3wfqs2":["gustavopessoa","Gustavo Pessoa"],
"aezrscr3gag5vevwbz4e2dwi":["hakasham","Pesado"],
"jxioptvib6opkk4gyvyq2drh":["hellostranger","Perigo noturno em pessoa 🦄"],
"kuahejsrexqc76r2qlpjgjzl":["heypesky","Pesky"],
"p2hg46qlx3shqh5dyoua2mnl":["hypermishipeshu","Peshu"],
"eiveadhadpas7vckw4okzr7i":["ichpsjon111","Misko The Pes"],
"qlowv6wjquzhjmy5vh4d32x2":["igorspp","Igor Pessi"],
"so4fwafqa52eltuzd32nl2oo":["imaniiik","Gol pesar"],
"gl5fsinvzu43yraj6dh53a5i":["jackinnerpest","Jack Inner Pest"],
"hvfe5ahkfnivqcysb2jal4fc":["jaimepesquera","Jaime Pesquera"],
"gx5vau3h6yjyzdp4dgiyezyp":["jorgedu","el niño pesoe"],
"5zqoktfsabyddy47t5ao4gqo":["johnnypesto37","Johnny Pesto"],
"45maibcvznhe2gejed4dlgtm":["joako75","Joako Pestrensson"],
"lzjicoanp7ujxfwlmweizdd4":["jpescada.com","João Pescada "],
"r73czpidjgi7ldk6gm7pvzsb":["jpestana","Julio Pestaña"],
"b6mkf36aymuqazid5qzzukq7":["jsapessoa","Joana Sa Pessoa"],
"s5oqav7mdymsqfi6qhfdmspr":["juliapessoa","Júlia Pessôa "],
"iqp5anqsqiy75b7psljaxi2s":["juklien","Julien Peschard"],
"hjxadalck4v3yjmh2qp2vize":["junakuski","Jani Pesonen"],
"w25linhbg6acpq7dbb4fppse":["kadupessoa","Kadu Pessoa "],
"emktub36d7uvqktpn2furu4g":["ketchupagogo","Pessimist Prime"],
"ysxhfdhksecz64m2mon3ctxs":["krikalitika","Turing Pest"],
"n46rsczucnqrlmek6nx2cony":["kr00pesh","kr00pesh"],
"xwakc36lg65lyb76qjwbf3ee":["kvantipes","pes прокрастинує читанням"],
"5mbyeg4jmmwj4grldr63zs5v":["lapesanta.cat","La Pesanta"],
"5stftbt5glygolaaam7uq6oh":["lilpesto","pest"],
"6psl3bigyaqpuqozwbsdy3kk":["limbero","pesto eller kolera"],
"rhhqgzedwe5eybu4c37iuk3c":["lilianpeschet","Lilian Peschet"],
"loe4ko266gxa4rauhpcibhx5":["lpeslier","Lucien Peslier"],
"ihhpu4wcyeiqobfqmbmoj4a3":["luizneto","Uma pessoa CHATA"],
"o5zsog2svtibkyyuw26mrpop":["lucaspessoaf","Lucas Pessoa"],
"mv74fybmuxtkw5cxniq5do2y":["lucampesando","Luca Maria Pesando"],
"pkb75mmsn2j7xocwl6hxb676":["lxparapessoas","Lisboa Para Pessoas"],
"5fytchyecju6olumfdgqu3fp":["lynskoang","lynne “wet bulb” peskoe-yang "],
"o55cnkf4nveftm4gukucn7kh":["mauker","Maurício Pessoa (Pôneis Malditos™) 🇧🇷🇩🇪"],
"yoims643s6wllflyfeeuhl5y":["mahdi4ai","Pesar Khale Chkara"],
"qi2x665fk4j3i57v2oxaeqml":["matheuspestana","Matheus Pestana"],
"cg5ogitsoyfmwesacvlkgcni":["markpesavento","Mark Pesavento"],
"stgkzfdd7fspstr5ohe7nvg7":["matheuscba96","Gordinho Pesadão"],
"y4z5ssstq7m3i3sccbfch4yp":["mariapesu","Maria Pesu"],
"crs374njlzsxiz4y65vzlru4":["masonpesek","Mason Pesek"],
"darrjeqbn2wrtulitr5n5wz7":["mariapesado","Maria Pesado"],
"pfhj4gipd4c56l2hj5iraret":["mbpesendorfer","Mario Pesendorfer"],
"3hzzilupqylprhbhromt6sz2":["mechajoepesci","mechaJoePesci"],
"27hfyxpgzm7klrrihi3urhqz":["melekpesen","Melek Pesen"],
"ydwee7rwmpkgxdp3j2gyqd52":["mfpesco","Matthew Pescosolido"],
"i6sf5qwnkf4cfwfxqvqmtctc":["michelthealmeida","Que Gira Pesada"],
"6k4i4aec4uszxc2kqgmffdc5":["milkepescs","Mike Pesca"],
"rc4mk5vfl64b2bs3aj5awp7x":["miss-pessimist","Reiry "],
"ayeo6y275kmpdayy3sxhbr2j":["migpest","Miguel Pestana "],
"a4wjz7mlopgs3hxdurd353em":["mlambo","Pesky Historian"],
"j5tnedyqajltbzgk36b33yuz":["moderan","Duane Pesice"],
"betxbnjcixvzkd4kelevrdoh":["msturi","NR Pesquera "],
"d7xi4ib5jnm3xslyaejl22cu":["natepester","Nate Pester"],
"36zq246m3mk6udqf6trlubep":["nocturnalchemy","Stephen Michael DiPesa"],
"cevwtevgzrbw5esbkeynp3xv":["nopepesky","Pesky"],
"2i6ukvbd7qumv42t6wegldoy":["npestel83","Nico Pestel"],
"dkxn3xshoto2l42xvhs43hdw":["outrobreno","Breno Pessoa "],
"fagxftfmbwf5uql2gvx6nuse":["patryk.adeu.cyou","Patryk Peszko"],
"hekz2v5d4xgivvzn4vgtnev2":["patpess","patricia pessoa"],
"66ifud5nflmhvlngqxavze5k":["paulinajo","Paulina Jo Pesch"],
"uefwwxblbxzte2msovm46dgz":["pcallowv","Peshka Calloway"],
"64fnzoc5jbtt4rsdidzpslrf":["pestalella","Pau Estalella"],
"6zor7t3va2m5jzxsqt7pe4eo":["pespatron","Пес Патрон (нон-офішал) "],
"7jqjp4hqxnjec4hsnhaveskw":["pessoptimist","Pessoptimist"],
"7nvnng43seboe73s5khzmkfw":["pessimusprime","Pessimus Prime "],
"7z6cwljgxm2wna3ldtlq6dot":["pespodlsd","Лис с Терры"],
"a4tpaimt5oera4fxotwxyws6":["pesandrine","Pedrono Sandrine "],
"ar3he56e6whw5gvi3sadej5h":["peshir.nl","Jarno Peschier"],
"dcf6eqgk3o2avd2tn4hb2abb":["peskyjski","Pesky Jski"],
"eip2ux2joizj5ek5nqtrmnym":["pessoabrain","PessoaBrain"],
"esrm6pxqcgj35ol5d6zohcfk":["pestocrimes","Spooky Times "],
"fod6cxvarucql6clioabjdr3":["pestafterdark","Pest After Dark 🐀"],
"jn7bntmv5ty5ezogotz7x7a7":"pesometimes",
"jupadbq23s4mx5xbei25dnsh":["pestilencecat","Miri"],
"kghkvyr5tr6bjpkklp5qifji":["pesck","Pesck agora sem _"],
"kquincxxdinwnpuj66nobahy":["pestilent.one","Gibrietas 🐀 Vermin Halls 🐀"],
"ocwtw64672rts6asrvjju6a4":["pesi","Pesi"],
"onhw4xwp5iaaumeaphauwgen":["pespsanto","Paulo Espírito Santo"],
"rij6cedsoxdsex4iyrlbldei":["pes","Пес, пес, купи майонез🇺🇦"],
"s3333ium34v5zuo22en2ef53":["pestefm","Pedro Esteves"],
"sorgcp4kasgq7ehda57gapmj":["pesky-pudu","Pesky"],
"sznza3cp3iswv25fg2asl46a":["pescotapadiario","Sem Noção de Bem"],
"xfav2bzqgeh5j5qqg7fgrxmf":["peskytakeya","PeskyTakeya "],
"xzk6xy4g7kwr5rykhlivcucj":["pessoa","vítor "],
"yespeg3dfrmna6uxsgf4id5v":["pesquilinha","Clayton Xavier "],
"yqxorf663rluxn67d3ays7bs":["peskybat","peachy puffy"],
"z3qudzjjxbysqprh3xuoiqkt":["pestmode","Kick Out the James"],
"kagoez55khamuvpkqzwcl5fj":["pesar","Pesar"],
"mqn4qgggsdnskeskkd5al4fw":"peskychihuahua",
"knhxz3hpntpxm43tedepegtv":["pesla","Peter Slagter"],
"e4jgjqk255sa5j5jf7jcgdte":["pessimistsarc","Pessimists Archive"],
"vqjm3diifx4xjyzmiz7demmv":["pest","eezy pesteezy"],
"jzfr7gjiflkeiwtwhtw3nsoo":["pesh","Peter Saathoff-Harshfield"],
"ixmgpgzesn2ct2otxfbcuecv":"peskey",
"by5lnsdkabk3afgli2uvfrzk":["peuic.pessoas.dev","Pedro Cardoso"],
"t46oq4nugwjnuw337fhcrp7j":["pescare","Mahi"],
"74pught6m6slspw474la7bd5":["peskydancingkat","Karen"],
"lo6xt5wv5qtrrs6svxzw22gx":["pessimistjay","Jay the Pessimist"],
"r234k7f4qftnsfngzdiasm4q":"pestandpridest",
"u4p564m6ug4chr7vw4a3unl3":["peschkaj","lo-fi socialist trash"],
"gbbshplmlvujyujf2aqfw7go":["peskysky","Pesky"],
"c6w5xsoqwsfisgtkxfagehhp":"pesarack",
"nazixjzjau44xbfoau4uehpa":["pest64","Peter loves 🐈🐈"],
"7ex3t23yvde7en2k5ligkho4":["pesrona","پرسونا"],
"zincygheiiso3f2sy56qacqy":["pessoalouri","Lourival Pessoa "],
"g47ql3ozdvkiuqoautdthcr2":["pedropessoa","Pedro Pessoa"],
"ak5hromwofxqc3epq43qk4vx":["pessoagabi","Gabriela Sa Pessoa"],
"qx75hz4jnaxgh6glrlloubpc":"pes10k",
"rb3syddev6riuis5srvwon3p":["pestilencelive","PestilenceLive_"],
"yjpulky5kowz47hmrlwd4lkl":"pesilva",
"rmsmphykp5yzg5qketet2r65":"pesbelig",
"qo6uyhvn5g2iw4ac7n7vag3i":["pesadillasrec","Pesadillas Recurrentes@Antonio José Marquez"],
"ykfbmonwpkz7wy23zpcetnvy":["peskydyslexia","Pesky Dyslexia Parent"],
"r7cakjd2k3sojbplfkrfgxln":"pescatarian",
"pcodkerybdibzcxb6tac6glh":["peskyjellyfish","Mekaela "],
"kcisieprvuodfiwe4jyw5t3z":["pessimistadjacent","Julia"],
"oo2hd7lws7plllfhq7ttqck6":"pespz",
"gomi5name6z7royrao2db5mq":["pesone","페소네 PESONE"],
"xnab7rswzmh4kvis6yudtc7n":["pesecb","volpe artica"],
"k5pryfyaqg4rv3xdlzw6vsda":["pessimist","𝕻𝖊𝖘𝖘𝖎𝖒𝖎𝖘𝖙"],
"5bg4foxcr5p6oqc7xaozl76m":["pescavelho","Pescavelho"],
"lvxl5jdp3bn77ilyrqzkzltw":["pestebubonica","peste bubônica "],
"npthsss2jybcnvqz6ks7jw46":["pesianharu","Haru"],
"btp75j7oimbpdubpd23wqxgc":["pessoamusical","Pessoa"],
"jpoi24ibqspkcumkuqpa7yjd":["pesce","pesce"],
"jpp54dvkaqowdcvp6cmflgky":["petrifiedfruit","anita pesh"],
"h4zvtguw7ly4vtpuvoay6gpe":["pestoenthusiast","Spencer Hibnick | Pesto Publications"],
"pey4pvgxfgioai7lwdtnqrjf":["pessimism","Aria"],
"c4zme6kujwplu5xas343hxfm":"pesconent",
"k6ci2hzoplhep327rsfc74be":["pessego","もも"],
"s6n5kt47qqja75ucvwnqfums":"peskyface",
"awyrjtmwxjdhuqpyetmj57uq":["pesci","Ethan/Ezekiel"],
"ft2powfa3amheblr6molrupg":"peshchise",
"jdfpfgnkvcrh3pcqwohkzykv":["peskymel","Mel Hulst"],
"7m2dbroy5rqr55pkeimd6v3a":["pestcontrol","Exterm Inc 🪳🐜🐛🐀 Orlando Pest Control Service"],
"4jtrjn7ibeegtsecty7o4uug":["peskyplumber","peskyplumber"],
"wxuyhfd3bdshybmdnzmpa57g":["peskymillennial","Chelsea"],
"ppdnvnh2co3qg2chjauemkzt":["pesodream","Peso Dream"],
"h6him4i2ex3fdwb6hw7scq7h":"pescina",
"t4ytrtj5l7vmprrdjsdseuds":["peskitoymedio","Peskito y Medio: Tu Podcast Friki"],
"gzvw7fya2fqirqjb3m4lhizq":["pescacosmica","Momo"],
"khftgx56cxqajaomudjlrlhs":["pesettimhera","Yusuf Özer"],
"o6a3zxouqkvmteykdhmn2wwp":["pesilla","236"],
"xmm7xdjcqtxacqfadzmyprse":["pestcontrolpod","Pest Control"],
"qmwptmid4lwob4werqwllty5":"pesely",
"loz7fj5mrdyuff4y5juumfvv":"pesto",
"hpm5yhscofimxv2zwdw5dauo":["pessperelyak","Пес Переляк "],
"p7t2a4lm75dsf43ghddcxaqd":["pescado","Pascal"],
"twhi2m6pm4pckdgzljhyy3rj":["pestilence","backlog dot hell | 🎮 BG3 "],
"t3hjl2t4wfqskryk7ip3kwmz":["pesk","PESK"],
"g6k7kndoy6bhivvlkcfp2kq6":["pestogeno","Rosé"],
"fdx6ahahn5aerdr5rscfeqn3":["peskaroo","Peskaroo"],
"ux5gpfv2xkyrpmgm4rezfftf":["pestpruf","Pestpruf"],
"reir3s3zxbsmjeokkcb7flaf":["pessimocidadao","Caio | Kyle "],
"5trdvabi3iodmw347nwsiee5":["pesteven","Peter Esteven"],
"hc3wmkzrcjq56y33yqn2kbi3":["pestonaquest","pest"],
"xtrqkkswdycayzi2v3mwkzih":["pescenic","Nicole Lyn Pesce"],
"n7ycvvhfh2vbxdl6kte2pfxq":"pesse",
"t2e3kbi3i5ueulmb4rbiwylr":["peststadt","marc"],
"ab3yhaqarw2qnsnesohty4dz":"pestelle",
"r42ktv447zh4qmet6jkuwxzq":"pestdoktorlive",
"zykcaft4sdpjrmv3imsg642x":["pestiesti","Steve Luck"],
"ipnmnditfryry7iiibf2etq5":"peskyfly",
"trpc5tzbxu2shpmrbaqlwui5":["pesti","Pesti 💙"],
"o7vlhsjltwlnrdjz36e7pwaf":["pesticle457","the very real smosh"],
"6ru3fxfqfkh5b7uikt6xqh2i":["pestobesto","Pesto... of Mars!!!"],
"xiw2egklxomu6hwgpkvjs7bg":["pes-stas","elz"],
"52qxordkwwptscrszx3jlko7":["pesquinox","Pesquinox"],
"z3rpnlto3v3gc57zrqx6tfsf":["pestilencemorg","Pestilence"],
"w6q7v6o53mo47xsgsffh7kqx":["pes40k","pes40k (but in a good way)"],
"zeptmuvlmoj3vdjvarzigvr5":["pestocomics","Adriano | Pesto Comics 🇨🇦"],
"ivtkxlrwjpm3ax7cn2gn76fo":"pescorder",
"2o6osquekusnnzpmxgnwleve":["pesxguin","••••••••"],
"ipgvrnlk33ebxyjsoo6utwyn":["peskyrattigan","RKS"],
"rbwxrwdqaogwd5idy6l2ovgy":["pesky-pincushion","Pesky-Pincushion"],
"zahgzhw6lcir6dto7343elhs":["pestilencegremlin","PestGremlin"],
"lzvnhrie2ux53nuqvjt7tqe7":["pesil","Pedro Silva"],
"cp3nd3672ses777jdafbyfrn":"pesche",
"v6krrbewsbrvpip5vlcstzdm":["peseditorial","Peter Senftleben"],
"icqirwsf3ortjbzhyvnzbbms":["pestispesti","Caliber LeNoir"],
"5xrb5fwgxiqvlec7xjckhpec":"pesistratos",
"bh6owmts7n73hydn5ujtddqu":["pessoasreb","Rabixcu"],
"4vfctyvei2cxztgh7v5hilii":["pestfest","Lenna"],
"ishra6zaqqmakanmifkh7abj":["pesvshapke","Пан ФОП ногою топ"],
"paq34q4zx6adcnadzyqdlj3c":["pesadeon","Mahdi"],
"c4ogzdar5wq3dpprw2lpiuue":["pestofasta","Oliv Laprévote"],
"6yunnj63kvmuyortonhl4r4t":"pesimistesmilay",
"japdf2thd5axbndkxknl5rzk":["persewald","Pesewald"],
"3urrpb45mmt7zviitgnz4w5e":"pespatroon",
"7tpfylhviobhz3wskl33j7o2":["peso-panzo","ぺそやまぱんぞう"],
"hrmec5ji6t3ojwvyhf4gxfo2":["pessayist","Philological Essayist"],
"auyfmxbbrr4yxnmnved37tc6":["pesticide","농약"],
"awpq72owrlt23ddsqx7huyup":["pespedis","stephanie anderson"],
"pd6ufnqqieroex5ajpmpzl3f":["pessimisticpersim","Pessimistic Persimmon"],
"wquyd7ggojjvafbc42jcfpdo":["pespiga","Pablo Espiga"],
"j2vqfokujxfugmrust5yiiep":"pessimismgod20",
"rpclpvjtr4bhyg2wv4b6onh7":["pester","Pester Power"],
"pmru2iq45xosisgkmlvxfsvo":["pescayade","ペスカトーレ"],
"ifcgwofii7affjhz2xoi627r":["peskyb1rb","InsecureCosplay"],
"rcqcscpurrcpipyid4szlcxd":["pestmiez","Ariana"],
"mbjb73vv55o35balxcr2g6ck":["pesso","ぺっそ"],
"m6ty5xfnbw6cvmvlktgryban":["pescamara","Sourpeach"],
"jesowk6nfjrtgvjimntpqvim":["pesadillaparque","Pesadilla en el Parque de Atracciones 💅"],
"cxvxgies6zmhriokfufay5gq":["pesto-rat","PESTO"],
"tl3nn4y6xznglqi3rl6b4zaj":"pescebeddo",
"e4frli43jbp2yhvwleedsomv":["pest0sauce","Pesto"],
"rwhlwed6rtkb3atdv7o4r6o7":"pestyskillengton",
"zismwnmo6acnsilb7zlbd75e":["peshecito","Peshecito art (VGen)"],
"yfvlnwvbkul5ahggleg2yty3":"peslyak",
"qdhx4mo5da3qayakp6ozm2ey":["pestdoktor","Pesto"],
"ji3z6ttarvyyl6kyfmfgdfw7":["pessicolorado","Tim"],
"mgek77zngnxa2nn5x32gppwr":["pesto81","Pesto81"],
"fai3hynknvnw32hs26egf53u":"pesnerd",
"xdzzcjkld7it5h7alciuxblc":"pesky",
"zcnfmrqftmxt5vaytzzehzmi":"pessoawrites",
"4e7aji6giamjpodyewirvmaz":["pestinthestreet","p̾e̾s̾t̾"],
"vbt2p3upoqglo2xd32xdt7nw":"pescalune",
"v6bsog2ykbyetrbioc67epw3":"peski",
"x56mnawslm4qgdpvyjgcnumj":["pestomusic","Jon Silva"],
"zuxjubaronongbptpd4qpsl4":["pesidaver","Pesi"],
"m3yludj35kpib3gjy6ajwdpc":["peskyraccoon","PeskyRaccoon"],
"xlo6jdh7wvrd5oxifcs47lpr":["pescobio","Camarada Loly Jackson "],
"etvkv7qzezrmi25urtr6sdyq":["pesec","PESEC"],
"dfqvz22izqzbfkysyl33yrh6":["pespe","Bartholomew Area Rapid Transit"],
"uwhrspyig6lftgghajitdhqy":["pestilentposter","Hot Slut on Bluesky"],
"ue2od2kp2jaibwixcwbymlsr":["pescait0","Pescaít0"],
"wq4fiyhfafsyh32kxfsmpfpc":"peshang",
"oxrstvelytr27mjwuukiscqg":["pest0","pesto"],
"f2nreavvb636b3vkcxoybgt5":["pestywizard","Pesto"],
"onp3nkiic7p3cyoyifn72kf4":"pesimon",
"6t7r3flhkxti54padzkwogzg":["pescum","pescum 🐟🏥🚑🚲"],
"elfmlapuo3qmnrcr2do46jcl":["pestimistisch","Kompetenzkompetenz "],
"lwkufu4ctlu3mwwkotk5h6qd":["pestodn","Whomp whomp"],
"4mznflmrxovc2rv2yptrjx2y":["pesteetcholera","Peste & Choléra"],
"vms4jnfspadaf6t6x6sti5ud":["pestui","Petra Stuiber "],
"47agaixk2ele77bjpwwrf4gv":"pestokathe",
"kqfxac2oumriugkzpunypy2s":["pespo","Pespo"],
"maeilgpgxxnnm6kxfti3a6se":"pestell",
"vgucy357khrf4bg5yqqdoed7":"pesttraum",
"gflqnocw7x7kdijhryg3zvkw":["pestororo","Pesto Roro"],
"heetgz2hylahv5wbzripk73h":["pesox","ぺそ©"],
"ti6dyux53444xwxvb2hc6dfv":["pesumatti","Matti Pesu"],
"topi4oyjon4lquzkj5i3ssjf":"pesselbach",
"6ne6gf5m5slfhhoqdcan4rd5":["pessimist00","ユキ"],
"bdjih2za6gza2buyksb44gim":"pesterchum",
"pntxggjl2bjv5hlmhineng6c":["pestopfer","Michael T.📯"],
"bv3qapdxluizs2dmzombyrct":"pesterev",
"d3kr2as4pc2got7ottw4nnpj":"pesceriso",
"jgz2fjlz25pkt5rrr67mshwj":"pesos",
"bpszak3drolxoudppez4kpdo":["pesbagnolet","Paris en Selle Bagnolet"],
"qre2hjlqpnqxktgb7ymykrdn":"pessimismgod16",
"ev7bi2yexbg74jny4ezk42nn":["peskyfox","Pesky Fox"],
"2a2dhyauhwgimyjzarfny5h7":"pessimismgod12",
"2x577w3bofalvpecpmffuci5":["pesansa","pesansa"],
"xeidql6d3xhacijqemmzgdvn":"pestoblues",
"4ln27uqldphmygv7itj22h7n":"pesito29",
"omtjaxqxbtbwup4mmr4veule":["peskyblue","peskyblue 👻"],
"4zsgilx43iywdpzqxonuuqjq":"pestowitch",
"vh4nxg4qfyyjdamxu66xib33":["pestiferous","Pestiferous"],
"xz224tieuc5xfy5few5aragr":["pestilentia-games","Alex Pestilentia Games "],
"nrxstunstu7j6pvh5zflqlca":"peskytimepirate",
"zg7e3ciasohjmtdlemct5jon":"pessimisticpossum",
"li3ph4mm5li445s5csh4to7q":["pescador0","Paul Fischer"],
"eyxy3hrblipwjhms4uvomviu":["peskydetails","PeskyDetails"],
"ysi7pvoen7qhp5xpvfniehsx":"pesyk",
"lso3i22zkeb7urgnq24t7r6i":"pesta1955",
"5ehmaupl5h2gi4urfxr2tshx":["peskymonkey","Pesky Monkey"],
"g3joiqpne4nsnjqnhriudyns":"pestohyena",
"ar22gcv5jul7uf2riksjpapf":["pessoanathalie","Nathalie"],
"ts5sz2hzkfqkgrwhqep7swcw":["pestilants","Gryphon 🏳️‍⚧️"],
"xnrrp6cymbyzgeho6tpug5on":"pespereta",
"rrpp2xmz2ies7dflrtgpsiqy":["pessimisticcomics","Pessimistic Comics"],
"kjgshydlxyxnh4k7q3yxw3fz":["pestopato","Pato"],
"y5cezemlvm2qyuxr7gux54hh":["pesmontreuil","PeS Montreuil"],
"nbwq6yasexdyyxctobuj52cl":["peskysplinter","Pesky Splinter"],
"ypllz3uu7qnqzgfmptjih57f":"pesu",
"h64y5a7am5iyhl2ftn6ecshk":["peskycat",".peskyy"],
"d6k4ntev6xdcu6fqsms7vukv":"peshmerga",
"t72nvcmzwhyhf4xntolmsejw":["pestoz","Chris Lowe "],
"ibd2uoz3qtmuqnkcdnctnxdp":"pestco",
"zifpqwjtdfeoccavrmbabxjz":["pesejdi","Petra Čagalj Sejdi"],
"bnualinbjhuekzzcw73jj7hf":["pesesina","Maria"],
"y2ywzo7iwjoqau5oesimx4ed":["pinhoone","Felépes"],
"52lziufgby3vleutezxcnfw6":["pipsqueakbat","Pesky Bat 🦇"],
"63xnxoc4yr6htweflhbhzjhx":["pistachio-pesto","Cheyenne"],
"o6knws3vkenabektyqs3m4d6":["plalotaris","PESTILENCE"],
"y2z6eilpvmb63ir4ttrq5m5k":["pntoine","Antoine Pestel"],
"polpk73kf5x6wd35bhvcutbn":["porange","Pessimistic Orange Art"],
"uaomuk2gmpuhl4xy7qmn7m62":["powtergaist","Pessoa inegavelmente normal "],
"7l6e3qsxt2jtpcknpveggx3w":["polborta","Pester Drivel"],
"vfcbsw2wajl2qb5xq4wcvsxb":["potentialzer0","Pessimistic🌦️"],
"5vh32nz6qnld7jv3wxonfiuc":["problemcic","Uočavam pesimizam"],
"uru4vu6gznvkmpeq2zkc2pvf":["proustianmess","Vera Pesata "],
"rcxnrpabmgprmchmosoojrp5":["purplepest","Purple pest "],
"ayz2haen2twfp3oub4ge4p5j":["puppester","That smelly pup, Pester"],
"ccuuvhnzrl3jd6mbrorkqqgq":["raypesina","Ray Pesina"],
"homgjoytommzfru34g7balip":["randypestana","Randy Pestana"],
"llg6v5vy2rlhsldlhu57barw":["relvap","Ariel Pessach Rubinstein"],
"ze6sbgulvezk6w2n5pbtjawr":["robsonpessoa","Robson Pessoa"],
"5qmxza3o7mtw66y6zhv52tlp":"saint-pesto",
"hjsdiu6krjpnc5kfflaaoedr":["saucepesto","SaucePesto"],
"i7idwzyqa6sf5pfdfsxgg357":["sahaqiel","yersinia pestis"],
"copriikqvjvkm4rblyt7tha7":["schlafwandler","Jorge Pescator 📸🎾⚽️"],
"tcyboqfcve7vj45eodbra5mp":["seanpesce","Sean Pesce"],
"pl22iee5zgwkjkglk3agy4sq":["sepessin","Sean Pessin"],
"4nqstp6btjljcjquw3elxlup":["senhorpeste","SenhorPeste"],
"oxl7hebwxbkaja3x5tlx235f":["sedapesen","Seda Pesen "],
"hfpfxqxpihrudnqxcayzzaj2":["sirpestilence","Pestilence👨‍🔬🦇"],
"67jaxbplrjbmfqeytr5xar64":["slimypest","pesty🪱"],
"3ppryjrqpbkmxrcywmmcrhz4":["sneakystripes","SNEAKYSTRiPES 💖"],
"viy4cjrgjiyy64l2uiwep53r":["stefanopessotto.com","Stefano Pessotto"],
"yxyiqd64wnuedbugv3zgh3bm":["sturzgetreide","Ishab Peschbay-M'Dengge"],
"eo5sjzrf2pr3bhrl33t3qnfd":["steffenster","Steffen Peschel "],
"cfdyu64lyelw5m7gtt3cd4is":["superpes","Pes Superbrat"],
"ryaye7el4nxka4snlukxbkzw":["tarsisazevedo.pessoas.dev","Tarsis Azevedo"],
"ygfa5v6y2hyphguxngqzbv5e":["tarcizo","pesteruim ✨"],
"bfzuuc5he7pdsazua63b3hrc":["talvez","Talvez Pessoa"],
"t2w4hbw6w4piarvgmdofozrg":["thallislp","Thallis Pessi"],
"ohndlb73a4waw3kph3m66dv6":["tielpi","Thierry Le Pesant"],
"g6tg7hlcppimg3lkxwlncgyd":["tpessoa","Talita Pessoa"],
"jrueklwq2lx4txmljv72b7ai":["transtornadson","Dep. Pessoal Instituto Banana Preta ☭"],
"nr5jutrgzvssi2gpvvvh47es":["tudlen","Pesto Dawg"],
"nm2bekor5sp5fbcggys7rxxf":["ty-pesh","TY-PESH"],
"ipjrx3vua7mmagg6psjeectj":["unpesomuerto","UnPesoMuerto"],
"kpd27yz6kqjlduisbblwxujj":["vazpraonde","uma pessoa muito tranquila"],
"v523qlpxga4wveshngjg63pi":["vaquinhadojubileu","Pessoinha de Pelúcia "],
"w37dyzlwkoq2qkwgipp5ffhq":["vascopessoa","Vasco Pessoa "],
"5frltstborntshe7tlyeocci":["valeriepestre","Valerie Pestre"],
"nocly35u234vjcsyfe3kn6ce":["verohime","Veronica Peshterianu ☕️"],
"udt56kpqfb36im7rq4wxyoqu":["vittoriopescatore","Vittorio Pescatore"],
"jwxdnrt63lvyz3pbhslkjdln":["vitorpessan","Vitor Pessan"],
"ri52sx3r4zvedcua4qt43xeo":["westofrome","Patrick J. Pes-Pass the Candy Corn"],
"6m3qyjse4bszfiyceu3bh7h7":["williampessoa","William Pessoa"],
"bkgt6bzfbmucoie2pglf55nc":["xinder","Pest"],
"6ubmqkctox7crlr66o5gfvn2":["yersiniapestis","Yersinia pestis"],
"lkcaqjggzsvimk64zd3alik3":["yersinapestis","Yersinia Pestis"],
"nec7m2eddnql74dd6wtojty3":["yersiniapestis76","Yersinia Pestis Ⓥ"],
"nllubpsgqza4u5pmg76tsih4":["zatopesto","Croque Pesto Vegetarien"],
"33as7o3cjra5wyo265f5so3t":["zealpalace","pessoa normal"],
"p54nki34utqk2mwirkxhr6wf":["zerostars","Cautiously Pessimistic"],
"tdvxi23eigdtfrnvgfzzsiek":["zhyrnyipes","Zhyrnyi Pes"]
}
