{
"7qiek3voe72juahgb2wpqqho":["kelepokepik","Quelle époque épique "],
"4gpew7vb66qaztqq4hnhhpym":["poqu","poqu"],
"uk6gfjg6qnqgukemjdis42k3":["poquitobird","PoquitoBird - 'Realms of the Fallen' Web Comic"],
"xnhmvlyuqezp6ystkr3m4iky":["poquil","ポキール_バンビ"],
"gk7hsnteuv4htn2isq7oq6oi":"poq",
"3gz7uvwer236id4mupird37g":["poqw135","키위"],
"sii4arsx27uz7mzpu3fimmfv":"poqjournal",
"ep5v5uqn6qdanqdjjly4y532":["poqpie","P a u l a"],
"qfk27bwqhra3pf5zjl75vdgi":"poquito",
"fwljioeqhihrczqpla4vlley":["whyknd","poqu¡to"]
}
