{
"v65f32kd6ncqat6xbyhkacht":["3phr","3phr"],
"o2jfswybsu4nvr2ldw7ku2lv":["acidphreak","Acid Phreak"],
"cdvjywvqnjeqdsjjjs7qu4hv":["aestheticphrenetic","Aesthetic Phrenetic "],
"whv3amu35bhgklxkv55fedvv":["agenttwelvetoes","🌕Phronesis🌑"],
"wnconpmv2fhnpzzjkgrtpqrt":["aladin","Phr. Aladin "],
"m2gg67hravbslm4inpc62pl4":["phreekz.de","chmee "],
"quacyqxgibfam3hq7serl46g":["chrisophren","Chris O'Phren"],
"eoba7je7gcb3mprkm3krygcy":["dertotmacher","Gloree Boxe the Penis Phrenologist"],
"br7sey7czsijbf3slu27o4iy":["dfw73","Phred"],
"354t7arur54bvg4gtfgc3jy4":["drphred","Dr Phred"],
"vce6ketn63smntt5hlcssv76":["feralbutterfly0","Phryne"],
"mtn3qlkvtacgo5t6ctvh5ec4":["jezmund","Dougie Phresh"],
"odvlwvqwvnbemx5av6uzde7b":["judgejames","James, PHR⚡"],
"jnyjqpfefunjt33whdquk2nj":["kur41","Phronesis"],
"bfzapngtkyxw4bwe432jadev":["littlefeej","Phred"],
"xl5n754fhz3u4rnig43sngl6":["markphrancis","Mark Phrancis"],
"wghnbogf2mtrp3mgdvrm3oso":["melleora","mel “parenthetical phrase” leora "],
"25inhjqgt3szvgp75iqbjfj2":["phroz","phroz"],
"7gos53wifk5jva4ij4cfvm2k":["phranz","François G."],
"akkhj4jcncoeiclisicfdqnf":["phrostknows","Aaron"],
"bkjxizsxmeyw7ceoaro43rzf":["phrynephisher","King StephieD"],
"cso36pocekumqdihhkmx2vtw":["phraggle","Phraggle"],
"cudtu3t333musirspqgnrnsc":["phrantastic22","Francesca Meaux"],
"f464onyg3myjh5qzgfjl4dfz":["phroureo","phroureo"],
"gukpuab3476rvmkayq2vznln":["phrichards.ca","Phil Richards"],
"hwdkuaqupwqxrtz3btsrx56v":["phrly","Peter Hurley "],
"mg26ff2uaysmbpxr2pequeuq":["phryx","Ecto/Phryx"],
"mor4ruyocijdl5l3mbbusvpd":["phroobin","ROO! 🏳️‍⚧️"],
"pxuwfz4ck6tw53du2zf2z7z4":["phrecklesart","phrecklesart"],
"s6xfmkr4h3jdopgvoppnt27e":["phrozin","Phrozin"],
"tlxvuad32cufrldycmf2opni":["phreddie","Phreddie 🍺"],
"tzb3p7eekyqo3as4m23a7yvv":["phraktyl","Wyatt Draggoo"],
"upfrgnhw3gdgg2rnpf4mqw7l":["phrost","Jim Casale"],
"v6u5qq4ednjgzc5gdjq54ngu":["phrebh","phrebh"],
"vcqy4df63cztqhrnkmr4lvsc":["phrozen.com","Henry Cole"],
"xdokbdgzzpidcdihhtmngm6q":["phrogelicious","Phroge"],
"yb434k75shnjchnz3ghajdek":["phredington","phred"],
"yikg4o3iqriqo7rzz6ryuodg":["phrancq","Phrancq"],
"ym6fa4vk7wqcwi2jvrdmgxhc":["phrobitey","Aliza "],
"te2bnhnt3lqgwtrs2qexaubq":["phrcarvalho","Pedro Henrique"],
"bkrbaslkq3yz64nhkkgf6ahb":"phreaky",
"nrf7gbdmis2r6culcyzqgx74":["phraselyweirded","Jaz"],
"f6fgrbsovmtcltgduxq6kqsl":"phreckles",
"bwkx2rvw5lhih46exzmca6vt":["phreck.com","phreck"],
"jniyv7pqn34mkuebxrnpqdrq":["phredmoyer","Fred Moyer"],
"gsxyeuus4ixvxy5d4sjisfs4":"phred",
"k75hmfo65us6cms7wkz4fvlb":"phreak",
"7nzklffvx6nsekgt3s47yobl":["phreakinggeek","PhreakingGeek"],
"ivwo44p6ttwiejz3eymzqe7y":["phrawzty.com","Dan 🌈"],
"4ruuzt4qm2ne5uvvb5o6wa36":["phreakocious.net","𝚙𝚑𝚛𝚎𝚊𝚔𝚘𝚌𝚒𝚘𝚞𝚜"],
"xb5esvubbhzbk4bifbdohuar":"phranqlin",
"e5rzt23os2khl6h65ddrmks5":"phrocha",
"hpndvjyjoindxmywgen3h5se":["phranchize","Primetime"],
"6rzypszve3xavyetxit7aa5p":"phrachtal",
"4yjs634cjjddszf44upnxbz4":"phranang",
"4obxbcpnthbzo76q4rph6hzb":["phrisk","LYDIA ZANOTTI "],
"tbrja4kbdfbjh2htrm2tz73l":["phrequencies","Presley"],
"bsier76u2kgl5gpe5rwyuuyd":"phreschke",
"nqhdk55kqt5ylpvoapilpwzv":["phroglegs","McKenna"],
"rx4gehlei32oku2uybx2zn52":["phrase","𝐏𝓗ℛ⃛эŠ𝑒"],
"3xiweuq46pysyml5idhvoa7r":"phrank",
"5fqk3jrvatcb743n5cad5mgr":["phreakatron","Joe"],
"2crgew2iuy63vcms2xhc2rht":["phreak80","Phreak80"],
"vrwtjde3e5yky6ivopl3yevv":"phranc",
"dj3rqlo34yeevoo6d5b2fzct":"phrgsrobot",
"rufpafnuy4sewv3awbyqx3wm":["phrankphernandez","Phrank Phernandez "],
"nh4eqqsrfkdwps3ckn2glq4a":["phraesia","phræsia"],
"hdvbkr6yayhzzhncmuzcucy3":["phredcetera","Phred Newman"],
"kczyf3pp7ds73v5vwdc4v2ks":["phronesis","Olaide"],
"xz6j6znxwvwv2tbrbaqzbopj":"phronemophobic",
"ex65p7dj4ivlk4ht6nqmhwcq":["phrunicorn","PHRUnicorn"],
"vzq2l44oemzysbwwbcdtbqgq":["phryne","Phryne"],
"xfrv23snq53m3cwqpasjlxtp":["phros","Phros"],
"ijeuzcol6cxfzxxly5kfzrci":["phrrmp","Phrrmp"],
"cmem3bshlg3r2kicgel4nliq":["phrisson","Moment Ends Tho I Feel Winds"],
"rts2uypzwibcmgp2zoojizp3":["phreddd","Fred V."],
"dmj6bowfyrf6mbl6jdrvozx4":"phreixx",
"xd4sgiwywhfcvzjwey6jbpjo":["phrlll","display name"],
"ardrio3cbfrs6upx3d6igt6r":["phreid","phreid"],
"zf4sotdlszxxniykuxjycrpo":["phreakclub","Phreak"],
"emhrqmgvm6bp5rsvxr4jqcav":["phrannd","Phrannd"],
"hldwd3enpjmxxp7237gpguil":["phree","potential trash"],
"fyu5hdnul5f3nw7p44ry7hea":["phrieken","phrieken"],
"uuvs6oudnvpywlgxyvihpoma":["phreakdaotter","BBnoOtty$"],
"t7bayz7jpp3t7cpvijdqhmdc":"phrankenstine",
"grnjokwqxd5fp6lw465r5hw7":["phrmir","쌉싸라디스"],
"g3ii7i4uiy7zxskom6glvbtp":["phrogofficial","Phrog"],
"yo73fiogchump3fzxotely3s":["philgollins","Phra 🦩 WHA brain"],
"f42crkugoeoeieyrnitnmqnh":"phrodlogg",
"5gispburgqxnxs4zg26jnavl":"phreakpisces",
"esbudx775cz5nydu4srbyar5":["phraseme","Michelle McCann"],
"xnltggh6q27ss2snel6g3skl":"phroghollow",
"whmg4acafknpixthyvrtopwp":["phrogely","Phroge"],
"xrg37nptmu3emaqbdlgeb6pv":["phrigid","Jolene Phrigid"],
"6yrgpansf7zzvvtsisvfddpx":["phronk","Phronk"],
"qyentuvqow5m55bdy3tueay3":["phrenic31","Phrenic "],
"hzn25afbmlimksfiiszimq3a":["phrax","Phrax"],
"pvmjnmv2sao4gyjdlx5xhtjm":["phr00ts","phr00ts"],
"n5pjreypbkrqmf5eaunayfom":["phrozenchemgeek","Peter Peterson, PhD"],
"7bh7lr6ek2newsfh4vdfwuoi":["phrysm","MIBRY🐣"],
"h2mtn63ltcoshuoqt3puxhkq":"phreneticspaghetti",
"roqvgoey5zuh6u3qps66525w":"phredlevi",
"rjtdzmf2eqf72mbmgqrobaig":"phroomis",
"7cysl4l6lcvmhkcbblowa7ln":"phr0zen",
"szksqbexmujwajdxandlxqnz":["phracktale","phracktale"],
"uy24nkjwmybjgh5yxfsjyjsv":"phrancis",
"aucezu3kisovclspvw6pf7mh":"phrosty",
"5k7tk3lttb25uznucpv5k7gr":"phrenicquake",
"sk7qnxro6kcgmtmg2ii7n6ef":["phreshlyshaven","PhreshlyShaven"],
"pofwiypfwgfbzis7quhqpnmd":["phraseneither","Eager Everybody"],
"5nwdfxuswfggamygegiq3ywo":["phreqs","não deiche o pau torar"],
"ppnnz76q4ct7nqt52awbvl4r":["phreezer","Ich mein ja nur"],
"nen3z3a7iebrh6zyzmsu4npf":"phro",
"jzbfaphrhxikie5ja5hjrrky":["phrozt","Phrozt"],
"5lfngxdimtnenzbyrejnd6mh":"phroggingaround",
"qmd2agox3asuwiypiqikftmn":["phruela","Talvez conhecida como a bo... Kkkkk"],
"k3ljmatwick6tdwt6td7tcw2":"phrogelf0",
"fqy4vfybj7qenp2rf3urjpig":"phresh",
"zajons4ze2a4xm7k3gvl5ef5":"phranziz",
"uwwmhqsi3nopygizmxc64dy5":"phrancisco",
"hyng5abw2kten7xjw436czed":"phrederico",
"lqhteqnm6nmet22rxi5eft7k":"phrewfuf",
"bytbdd2ump2losvvkbkgbbuz":["phrike","🐈‍⬛️ "],
"gbz3eeo3jvlaah65ih7hmpms":"phr",
"3tuzeet67yokt5a2rlww4ias":"phrygas",
"vvdqlfnit6icchv2ifusfd2v":["phrenk","phrenk"],
"y7anhvupjfe6ltqm52rnv47e":["phranklin","Phranklin"],
"54clzsrxeimstto54d52tq4w":["phriarkun","Phedro 🪸"],
"ol3hlxsph3e2jste7iph3nqa":"phrobaby",
"gi4preong4l2ayfckmownmzt":"phrases",
"ux5kjmy5gpqnth5ono3xb6xp":["phreako","Phreako"],
"2snhvpg232e3kusz7ii2zokk":"phrogelf8",
"xlkvxshzpsc4urw25mtla6t6":["phrolick","Cédric Arnaud"],
"wpv4alkewld3trwxwcryvpyr":"phrog",
"nppvrh3fcs5ri74zebjt6aw5":["phry","Dominik Felhofer"],
"aj5n3cn256p6ayy5iphxdxjl":["phrogprince","Tentacles Squelching Wetly"],
"f3d7w455qmk7d43edfeut3ix":["phragmites","Phragmites Ying-Ko"],
"i55lzyxl4mros3kdsnnzijhj":"phreadd",
"g6i2dugfdycpefxicpni76iw":["phrixos1973","Þh®I×Ø§ / Φριξος"],
"odtlwaihrm4omrrin5b5ws25":"phrhiedom",
"gm5xzaqwb7ubs3hoirf4t4ut":["phrasentrasher","Yoda Posemuckel (Brigitte_Dreadhead)"],
"xbnunziqe5hupoewmifv7rrv":"phrogelf5",
"m5nanghwfkavbgdws5zczccg":["phrm","Ephraim Chaney"],
"n5lqy7yggvprxninng4poqko":["phreakattack","Phreak"],
"ed5ydqofijfbioconrl2pl2b":"phreshchuck",
"btlhirjx4iwy6mrxbf3tla56":"phrin",
"xwepplzr7hphr55jseie4a75":"phrickshun",
"p3yxuyuaxh4dyjabqunhuezj":["phr0g","Phr0g"],
"mxehvicw7ng26liepzbkxvnj":["phrisque","Phriss"],
"c3f67nw4sjf4qdpvkzieqxyn":"phrogg",
"7uqrxoichddipn3p5fqd3tje":"phreeloader",
"qe3vitjmrlbx7hlqqjabh7kg":["phreehawk","Twitter refugee #10383920"],
"drjq54aerfvhrhsg6xh4zfc5":["phrasendreher.de","PhrasenDreher"],
"wx4yivbnkztie4aqebukh34o":["phrakete","Frau Rakete 🚀"],
"h7sbvdryx3xjua7x2wfwajlj":["phrey","Philipp Frey "],
"7be3dzck3qad43orfu5p2ukg":["phrog36","Phrog"],
"odxwapwewknabfhwz75r7cmz":"phrenic",
"2reamlhk27nm3jd62tkrb6wp":["phrais","phrais"],
"r4d6mwe5m2gniiab5jad3eam":["phr34k","Phreak"],
"o6465xolvjtvj3msppnaqs75":["phreddo","Phreddo"],
"g6dep2tatzoaffj4jecz4jjf":["phroggu","Phroggu"],
"d4drr6zwhiuxjwagopwaykj3":"phroggi3",
"eub5vkxcfid7aht4c4dkbs2c":["phrostbite","Vanessa Xuân "],
"hwj34b4dut6hhzrglkaszdh5":["phrogly","Phrogly"],
"4iqpt4rmfabhx3ulbne76co3":["phreds040","Malmeño"],
"5uk2fc6c4lig3j6tdt7mwohm":"phripheoniks",
"v3jbxe76fs4mkjovl2ljuonj":["phraselnd","🌒 dnldblv"],
"zv7cgxl3zz2dxrrmnc3ii733":["phrixphrox","Phrix Phrox"],
"5s4bv7ji2r3ds4ykctplnsov":["phr0nak","Christian López 🦄"],
"ypdecxqlamyyyqti74dtirqn":"phrex",
"sutdnfuet7txtcfyltyh3kcd":["phrenonym","Phrenonym"],
"jipll725i34fmoyif4gmwmcz":["phreshbeets","Davey "],
"afjrec2rrodofvvnkmgvszre":"phrajil",
"awng6idjvz6tcd2ocv2blyx2":["phrux","Phrux"],
"db6wytctrxsswqe7axbbbi2q":["phreespeech","molotovs against malarkey"],
"pat2e67nvzb3wrwkm7race74":"phreedomjawn",
"5cr4d7ot7gd3g5nvsqzvrnpe":["phramewerk","Seán Ó Murchú "],
"2jfkm2zwgunafwg6exgcx5b7":"phryyne",
"rc4dtncuyjsuarcs3j7orrqx":"phrogelf23",
"urqchmbkuzhryt2py3bbyunm":["phranque","Phranque likes football"],
"cfcl5x5zvcopa6cbfymszqxi":["phrim","Doug Faust"],
"733n3ftm5ryh766sxyayoos7":"phrogelf19",
"uguveevrvj6tzlw3goap7uma":["phreek","PHREEK"],
"qorcqip4bjxcjbsv3fk7fn2k":["phragments","Carolyn"],
"ogjlp2epjue7vv73ef3g5t5i":["phreakstation","phreakstation"],
"udvhk53hmkeho7zhsbowfqoa":["phrutbat","Phrutbat"],
"bfwr2y6btzrf2ce3ifgbh7ih":["phrubes","Pavel"],
"eizfcp6j3ok3yzc7gwyqjdpz":["phrenesis","Teru Jekyll"],
"kfcpozdek3q3hmj6q7jdhx36":["phrogunderscore","Charlie "],
"4xjz56xdwedvooj5yebkhbc2":["phraio","Raio"],
"tfgqo7gevqik7yeyjfwzbz4u":["phraggel","Jonas Cronholm-Lundin"],
"eqakztquqcmhwaemotbefxwz":["phred-cheng","Fred Cheng"],
"caldnsz7t5zkwjsvibdxo7lh":"phrenssynnes",
"egi3s7hizee3flxd2ow5tzmk":["phraenk","Phränk"],
"4wuvqedogdirbob26frszvks":["rhandomphreak88","RhandomPhreak"],
"nsfke7cou56277m3hlgrukrl":["scorchsky","Phx Phreeway Phoets"],
"dnjad54duzajukkbnqv52hc4":["shempstielhope","Phred"],
"quqv56q2bwhxdldr6mvndz3x":["su1phr","Su1phr"],
"wjbleq3lppqb2c6b6krvfm2e":["touchingtheveil","Phraya "],
"v5hoy2agex7kdnhbl57unqfk":["phridou","PhRidou"]
}
